setup.py
xuchangxin/__init__.py
xuchangxin/demo1.py
xuchangxin/demo2.py
xuchangxin.egg-info/PKG-INFO
xuchangxin.egg-info/SOURCES.txt
xuchangxin.egg-info/dependency_links.txt
xuchangxin.egg-info/top_level.txt