Metadata-Version: 2.1
Name: xuchangxin
Version: 1.0
Summary: 这是第一个对外发布的模块，测试哦
Author: luoluo
Author-email: 910817507@qq.com
